cryton_core/__init__.py
cryton_core/asgi.py
cryton_core/cryton_app/__init__.py
cryton_core/cryton_app/admin.py
cryton_core/cryton_app/apps.py
cryton_core/cryton_app/exceptions.py
cryton_core/cryton_app/management/__init__.py
cryton_core/cryton_app/management/commands/__init__.py
cryton_core/cryton_app/management/commands/runserver.py
cryton_core/cryton_app/management/commands/start.py
cryton_core/cryton_app/management/commands/startgunicorn.py
cryton_core/cryton_app/management/commands/startlistener.py
cryton_core/cryton_app/management/commands/startmonitoring.py
cryton_core/cryton_app/migrations/0001_initial.py
cryton_core/cryton_app/migrations/__init__.py
cryton_core/cryton_app/models.py
cryton_core/cryton_app/serializers.py
cryton_core/cryton_app/urls.py
cryton_core/cryton_app/util.py
cryton_core/cryton_app/views/__init__.py
cryton_core/cryton_app/views/execution_variable_views.py
cryton_core/cryton_app/views/log_views.py
cryton_core/cryton_app/views/plan_execution_views.py
cryton_core/cryton_app/views/plan_template_views.py
cryton_core/cryton_app/views/plan_views.py
cryton_core/cryton_app/views/run_views.py
cryton_core/cryton_app/views/stage_execution_views.py
cryton_core/cryton_app/views/stage_views.py
cryton_core/cryton_app/views/step_execution_views.py
cryton_core/cryton_app/views/step_views.py
cryton_core/cryton_app/views/worker_views.py
cryton_core/etc/__init__.py
cryton_core/etc/config.py
cryton_core/lib/__init__.py
cryton_core/lib/models/__init__.py
cryton_core/lib/models/plan.py
cryton_core/lib/models/run.py
cryton_core/lib/models/session.py
cryton_core/lib/models/stage.py
cryton_core/lib/models/step.py
cryton_core/lib/models/worker.py
cryton_core/lib/services/__init__.py
cryton_core/lib/services/gunicorn.py
cryton_core/lib/services/listener.py
cryton_core/lib/services/scheduler.py
cryton_core/lib/triggers/__init__.py
cryton_core/lib/triggers/trigger_base.py
cryton_core/lib/triggers/trigger_datetime.py
cryton_core/lib/triggers/trigger_delta.py
cryton_core-2023.1.2.dist-info/entry_points.txt
cryton_core-2023.1.2.dist-info/WHEEL
cryton_core-2023.1.2.dist-info/METADATA
cryton_core-2023.1.2.dist-info/LICENSE
cryton_core-2023.1.2.dist-info/RECORD
