Metadata-Version: 2.1
Name: cryton-core
Version: 2023.1.2
Summary: Advanced scheduler for attack scenarios
Home-page: https://gitlab.ics.muni.cz/cryton
License: MIT
Keywords: cryton,core,advanced,scheduler
Author: Ivo Nutár
Author-email: nutar@ics.muni.cz
Maintainer: Jiří Rája
Maintainer-email: raja@ics.muni.cz
Requires-Python: >=3.8,<3.12
Classifier: License :: OSI Approved :: MIT License
Classifier: Programming Language :: Python :: 3
Classifier: Programming Language :: Python :: 3.8
Classifier: Programming Language :: Python :: 3.9
Classifier: Programming Language :: Python :: 3.10
Classifier: Programming Language :: Python :: 3.11
Requires-Dist: AMQPStorm (>=2.10.4,<3.0.0)
Requires-Dist: APScheduler (>=3.8.1,<4.0.0)
Requires-Dist: Django (>=4.0.1,<5.0.0)
Requires-Dist: Jinja2 (>=3.0.3,<4.0.0)
Requires-Dist: PyYAML (>=6.0,<7.0)
Requires-Dist: SQLAlchemy (>=1.4.29,<2.0.0)
Requires-Dist: click (>=8.1.3,<9.0.0)
Requires-Dist: django-cors-headers (>=3.13.0,<4.0.0)
Requires-Dist: djangorestframework (>=3.14.0,<4.0.0)
Requires-Dist: drf-spectacular (>=0.26.0,<0.27.0)
Requires-Dist: drf-spectacular-sidecar (>=2023.3.1,<2024.0.0)
Requires-Dist: gunicorn (>=20.1.0,<21.0.0)
Requires-Dist: psycopg2-binary (>=2.9.5,<3.0.0)
Requires-Dist: python-dotenv (>=1.0.0,<2.0.0)
Requires-Dist: pytz (>=2022.7,<2023.0)
Requires-Dist: rpyc (>=5.3.0,<6.0.0)
Requires-Dist: schema (>=0.7.5,<0.8.0)
Requires-Dist: structlog (>=22.3.0,<23.0.0)
Requires-Dist: tzlocal (>=4.1,<5.0)
Requires-Dist: uuid (>=1.30,<2.0)
Requires-Dist: uvicorn (>=0.20.0,<0.21.0)
Project-URL: Documentation, https://cryton.gitlab-pages.ics.muni.cz/cryton-documentation/
Project-URL: Repository, https://gitlab.ics.muni.cz/cryton/cryton-core
